FleetingViews.py
fleetingviews-0.2.dist-info/METADATA
fleetingviews-0.2.dist-info/WHEEL
fleetingviews-0.2.dist-info/top_level.txt
fleetingviews-0.2.dist-info/RECORD
