Metadata-Version: 2.4
Name: fleetingviews
Version: 0.2
Summary: Facilitates view creation and management in Flet applications.
Home-page: https://github.com/ArellanoBrunoc/FleetingViews
Author: Bruno Arellano
Author-email: arellanobruno@hotmail.com
Maintainer: Bruno Arellano
Maintainer-email: arellanobruno@hotmail.com
License: MIT
Keywords: flet,views,flet views,view creation,flet app
Requires-Dist: flet
Dynamic: author
Dynamic: author-email
Dynamic: description
Dynamic: description-content-type
Dynamic: home-page
Dynamic: keywords
Dynamic: license
Dynamic: maintainer
Dynamic: maintainer-email
Dynamic: requires-dist
Dynamic: summary
